mcp_ine/__init__.py
mcp_ine/censo2021.py
mcp_ine/common.py
mcp_ine/resources.py
mcp_ine/server.py
mcp_ine/tools.py
mcp_ine-0.3.0.dist-info/licenses/LICENSE
mcp_ine-0.3.0.dist-info/METADATA
mcp_ine-0.3.0.dist-info/WHEEL
mcp_ine-0.3.0.dist-info/entry_points.txt
mcp_ine-0.3.0.dist-info/top_level.txt
mcp_ine-0.3.0.dist-info/RECORD
