Metadata-Version: 2.4
Name: mcp-ine
Version: 0.3.0
Summary: MCP Server for INE (Spanish Statistical Office) public data API - Access 109+ statistical operations + Censo 2021
Author-email: sofias tech <sss@sofias.ai>
License-Expression: MIT
Project-URL: Homepage, https://github.com/Sofias-ai/mcp-ine
Project-URL: Repository, https://github.com/Sofias-ai/mcp-ine
Project-URL: Issues, https://github.com/Sofias-ai/mcp-ine/issues
Project-URL: Documentation, https://github.com/Sofias-ai/mcp-ine#readme
Keywords: mcp,ine,statistics,spain,data,api,model-context-protocol
Classifier: Development Status :: 4 - Beta
Classifier: Intended Audience :: Developers
Classifier: Programming Language :: Python :: 3
Classifier: Programming Language :: Python :: 3.10
Classifier: Programming Language :: Python :: 3.11
Classifier: Programming Language :: Python :: 3.12
Classifier: Topic :: Software Development :: Libraries :: Python Modules
Classifier: Topic :: Scientific/Engineering :: Information Analysis
Requires-Python: >=3.10
License-File: LICENSE
Requires-Dist: mcp>=1.2.1
Requires-Dist: requests>=2.28.0
Requires-Dist: python-dotenv>=1.0.0
Dynamic: license-file
